dtj/__init__.py
dtj/cli.py
dtj/file_utils.py
dtj/main.py
dtj-0.1.8.dist-info/LICENSE
dtj-0.1.8.dist-info/METADATA
dtj-0.1.8.dist-info/WHEEL
dtj-0.1.8.dist-info/entry_points.txt
dtj-0.1.8.dist-info/top_level.txt
dtj-0.1.8.dist-info/RECORD
