Metadata-Version: 2.1
Name: dtj
Version: 0.1.8
Summary: A tool to convert directory contents to JSON
Home-page: https://github.com/adriangalilea/dtj
Author: Adrian Galilea Delgado
Author-email: adriangalilea@gmail.com
Classifier: Programming Language :: Python :: 3
Classifier: License :: OSI Approved :: MIT License
Classifier: Operating System :: OS Independent
Requires-Python: >=3.6
License-File: LICENSE
Requires-Dist: rich
Requires-Dist: pyperclip
Requires-Dist: pathspec
